README.md
setup.py
NNBuilder.egg-info/PKG-INFO
NNBuilder.egg-info/SOURCES.txt
NNBuilder.egg-info/dependency_links.txt
NNBuilder.egg-info/not-zip-safe
NNBuilder.egg-info/requires.txt
NNBuilder.egg-info/top_level.txt
nnbuilder/__init__.py
nnbuilder/data.py
nnbuilder/logger.py
nnbuilder/main.py
nnbuilder/model.py
nnbuilder/extensions/__init__.py
nnbuilder/extensions/basic.py
nnbuilder/extensions/debug.py
nnbuilder/extensions/earlystop.py
nnbuilder/extensions/monitor.py
nnbuilder/extensions/sample.py
nnbuilder/extensions/saveload.py
nnbuilder/extensions/shuffledata.py
nnbuilder/extensions/tensorboard.py
nnbuilder/kernel/Mxnet.py
nnbuilder/kernel/Pytorch.py
nnbuilder/kernel/Theano.py
nnbuilder/kernel/__init__.py
nnbuilder/kernel/basic.py
nnbuilder/kernel/kernel.py
nnbuilder/kernel/theano_utils.py
nnbuilder/layers/__init__.py
nnbuilder/layers/basic.py
nnbuilder/layers/conv.py
nnbuilder/layers/kernel.py
nnbuilder/layers/misc.py
nnbuilder/layers/ops.py
nnbuilder/layers/param.py
nnbuilder/layers/recurrent.py
nnbuilder/layers/simple.py
nnbuilder/layers/utils.py
nnbuilder/models/__init__.py
nnbuilder/models/ganeration.py
nnbuilder/models/image.py
nnbuilder/models/standard.py
nnbuilder/models/text.py
nnbuilder/models/utils.py
nnbuilder/optimizers/__init__.py
nnbuilder/optimizers/conjugatemethod.py
nnbuilder/optimizers/gradientdescent.py
nnbuilder/optimizers/newtonsmethod.py
nnbuilder/optimizers/steepestdescent.py
nnbuilder/tools/__init__.py
nnbuilder/tools/datadiver.py
nnbuilder/tools/loaddatas.py
nnbuilder/tools/plotter.py
nnbuilder/tools/printer.py
nnbuilder/tools/samples.py
test/__init__.py
test/test.py